Buke_PypiMain/Buke_S002_buy_list.py
Buke_PypiMain/Buke_S002_sell_list.py
Buke_PypiMain/Buke_S004_buy_list.py
Buke_PypiMain/Buke_S004_sell_list.py
Buke_PypiMain/Buke_S005_buy_list.py
Buke_PypiMain/Buke_ST001_buy_list.py
Buke_PypiMain/Buke_ST001_sell_list.py
Buke_PypiMain/Buke_ST002_buy_list.py
Buke_PypiMain/Buke_ST002_sell_list.py
Buke_PypiMain/Buke_ST003_buy_list.py
Buke_PypiMain/Buke_ST003_sell_list.py
Buke_PypiMain/Buke_ST004_buy_list.py
Buke_PypiMain/Buke_ST004_sell_list.py
Buke_PypiMain/__init__.py
Buke_PypiMain/function.py
Buke_PypiMain/generate_day_price.py
Buke_PypiMain/generate_index_day_price.py
Buke_PypiMain/generate_kosdaq_price.py
Buke_PypiMain/generate_stock_list.py
Buke_PypiMain/generate_trading_days.py
Buke_PypiMain/generate_trval_data.py
Buke_PypiMain/indicator.py
Buke_PypiMain/parameter.py
Buke_PypiMain/tools.py
Buke_PypiMain-1.0.0.dist-info/METADATA
Buke_PypiMain-1.0.0.dist-info/WHEEL
Buke_PypiMain-1.0.0.dist-info/top_level.txt
Buke_PypiMain-1.0.0.dist-info/RECORD
