Metadata-Version: 2.1
Name: Buke_PypiMain
Version: 1.0.0
Summary: test source
Home-page: https://eu4ng.tistory.com
Author: yesben
Author-email: jh20212645@gmail.com
Classifier: Programming Language :: Python :: 3
Classifier: License :: OSI Approved :: MIT License
Classifier: Operating System :: OS Independent
Requires-Python: >=3.6
